{
	"url": {
        "FriendlyUrl": "/",
        "View": "/home",
        "Active": "True",
        "Indexing": "True",
        "StatusCode": 200,
		"Id":"2AF06EED-3850-4E78-B8AE-C3B325849F00",
		"Action":"/Template/Compose",
    },
    "url": {
        "FriendlyUrl": "/flights/cheap-flights-to-new-york-city",
        "View": "/flights/destination-city",
        "Active": "True",
        "Indexing": "True",
        "StatusCode": 200,
		"Id":"DDC59F96-327A-41D8-9E7D-20E23669D6B9",
		"Action":"/Template/Compose",
    },
	 "url": {
        "FriendlyUrl": "/flights/cheap-flights-to-las-vegas",
        "View": "/flights/destination-city",
        "Active": "True",
        "Indexing": "True",
        "StatusCode": 200,
		"Id":"D8AEE472-70DF-492A-B378-7F3AFFB94CCA",
		"Action":"/Template/Compose",
    }
}